laufband/__init__.py
laufband/cli.py
laufband/db.py
laufband/graphband.py
laufband/heartbeat.py
laufband/laufband.py
laufband/monitor.py
laufband/task.py
laufband-0.2.1.dist-info/METADATA
laufband-0.2.1.dist-info/WHEEL
laufband-0.2.1.dist-info/entry_points.txt
laufband-0.2.1.dist-info/licenses/LICENSE
laufband-0.2.1.dist-info/RECORD
