Metadata-Version: 2.4
Name: laufband
Version: 0.2.1
Summary: Parallel Iteration with File-Based Coordination
Project-URL: Repository, https://github.com/zincware/laufband
Project-URL: Releases, https://github.com/zincware/zntrack/laufband
Project-URL: Discord, https://discord.gg/7ncfwhsnm4
Author-email: Fabian Zills <fzills@icp.uni-stuttgart.de>
License-Expression: MIT
License-File: LICENSE
Requires-Python: >=3.11
Requires-Dist: flufl-lock>=8.1.0
Requires-Dist: rich>=14.0.0
Requires-Dist: sqlalchemy>=2.0.43
Requires-Dist: tqdm>=4.67.1
Requires-Dist: typer>=0.15.2
